[
	{
		"inputs": [
			{
				"internalType": "string",
				"name": "_name",
				"type": "string"
			},
			{
				"internalType": "string",
				"name": "_cateogry",
				"type": "string"
			},
			{
				"internalType": "string",
				"name": "_image",
				"type": "string"
			},
			{
				"internalType": "uint256",
				"name": "_cost",
				"type": "uint256"
			},
			{
				"internalType": "uint256",
				"name": "_rating",
				"type": "uint256"
			}
		],
		"name": "addItem",
		"outputs": [],
		"stateMutability": "nonpayable",
		"type": "function"
	},
	{
		"inputs": [
			{
				"internalType": "string",
				"name": "_name",
				"type": "string"
			}
		],
		"name": "addSeller",
		"outputs": [],
		"stateMutability": "nonpayable",
		"type": "function"
	},
	{
		"inputs": [
			{
				"internalType": "uint256",
				"name": "index",
				"type": "uint256"
			}
		],
		"name": "buyItem",
		"outputs": [],
		"stateMutability": "payable",
		"type": "function"
	},
	{
		"inputs": [
			{
				"internalType": "uint256",
				"name": "index",
				"type": "uint256"
			},
			{
				"internalType": "uint256",
				"name": "change",
				"type": "uint256"
			}
		],
		"name": "changeDelieryStatus",
		"outputs": [],
		"stateMutability": "nonpayable",
		"type": "function"
	},
	{
		"inputs": [
			{
				"internalType": "uint256",
				"name": "index",
				"type": "uint256"
			},
			{
				"internalType": "uint256",
				"name": "change",
				"type": "uint256"
			}
		],
		"name": "changeItemAvaliability",
		"outputs": [],
		"stateMutability": "nonpayable",
		"type": "function"
	},
	{
		"inputs": [],
		"stateMutability": "payable",
		"type": "constructor"
	},
	{
		"inputs": [],
		"name": "withdrawFunds",
		"outputs": [],
		"stateMutability": "nonpayable",
		"type": "function"
	},
	{
		"inputs": [
			{
				"internalType": "uint256",
				"name": "",
				"type": "uint256"
			}
		],
		"name": "items",
		"outputs": [
			{
				"internalType": "address",
				"name": "owner",
				"type": "address"
			},
			{
				"internalType": "uint256",
				"name": "id",
				"type": "uint256"
			},
			{
				"internalType": "string",
				"name": "name",
				"type": "string"
			},
			{
				"internalType": "string",
				"name": "cateogry",
				"type": "string"
			},
			{
				"internalType": "string",
				"name": "image",
				"type": "string"
			},
			{
				"internalType": "uint256",
				"name": "cost",
				"type": "uint256"
			},
			{
				"internalType": "uint256",
				"name": "rating",
				"type": "uint256"
			},
			{
				"internalType": "enum Dappazon.ProductStatus",
				"name": "status",
				"type": "uint8"
			}
		],
		"stateMutability": "view",
		"type": "function"
	},
	{
		"inputs": [],
		"name": "name",
		"outputs": [
			{
				"internalType": "string",
				"name": "",
				"type": "string"
			}
		],
		"stateMutability": "view",
		"type": "function"
	},
	{
		"inputs": [
			{
				"internalType": "uint256",
				"name": "",
				"type": "uint256"
			}
		],
		"name": "orders",
		"outputs": [
			{
				"internalType": "address",
				"name": "buyer",
				"type": "address"
			},
			{
				"internalType": "address",
				"name": "seller",
				"type": "address"
			},
			{
				"internalType": "uint256",
				"name": "itemIndex",
				"type": "uint256"
			},
			{
				"internalType": "enum Dappazon.DeliveryStatus",
				"name": "status",
				"type": "uint8"
			}
		],
		"stateMutability": "view",
		"type": "function"
	},
	{
		"inputs": [],
		"name": "owner",
		"outputs": [
			{
				"internalType": "address",
				"name": "",
				"type": "address"
			}
		],
		"stateMutability": "view",
		"type": "function"
	},
	{
		"inputs": [
			{
				"internalType": "address",
				"name": "",
				"type": "address"
			}
		],
		"name": "sellers",
		"outputs": [
			{
				"internalType": "string",
				"name": "name",
				"type": "string"
			},
			{
				"internalType": "address",
				"name": "wallet",
				"type": "address"
			},
			{
				"internalType": "uint256",
				"name": "balance",
				"type": "uint256"
			}
		],
		"stateMutability": "view",
		"type": "function"
	}
]